deductive_system/__init__.py
deductive_system/_version.py
deductive_system/engine.py
deductive_system/version.py
deductive_system/data/__init__.py
deductive_system/data/peano.py
deductive_system/data/prop.py
deductive_system-0.0.1.dist-info/METADATA
deductive_system-0.0.1.dist-info/WHEEL
deductive_system-0.0.1.dist-info/top_level.txt
deductive_system-0.0.1.dist-info/RECORD
