Metadata-Version: 2.4
Name: deductive_system
Version: 0.0.1
Author-email: Hao Zhang <hzhangxyz@outlook.com>
Requires-Python: >=3.13
Requires-Dist: pyparsing~=3.2.2
